src/edsac/misc/flipflop.v
module flipflop
   (output wire out,
    output wire out_bar,

    input wire  set,
    input wire  reset
   );

   reg outi = 1'b0;

   always @(posedge set) begin
      outi <= 1'b1;
   end

   always @(posedge reset) begin
      outi <= 1'b0;
   end

   assign out = outi;
   assign out_bar = ~out;

endmodule

test/edsac/misc/flipflop_tb.v
module flipflop_tb();
   reg  set;
   reg  reset;
   wire out;
   wire out_bar;

   flipflop ff
     (.out     (out),
      .out_bar (out_bar),
      .set     (set),
      .reset   (reset)
     );

   initial begin
      $dumpfile("flipflop.vcd");
      $dumpvars(1, flipflop_tb);
      set = 1'b0;
      reset = 1'b0;
      #20 set = 1'b1;
      #1 set = 1'b0;
      #40 set = 1'b1;
      #5 set = 1'b0;
      #7 reset = 1'b1;
      #3 reset = 1'b0;
      #14 reset = 1'b1;
      #3 reset = 1'b0;
      #21 set = 1'b1;
      #2 set = 1'b0;
      #9 reset = 1'b1;
      #9 reset = 1'b0;
      #45 $finish;
   end

endmodule

test/edsac/misc/flipflop.vcd
$date
	Sun Jun 11 20:29:33 2017
$end
$version
	Icarus Verilog
$end
$timescale
	1s
$end
$scope module flipflop_tb $end
$var wire 1 ! out_bar $end
$var wire 1 " out $end
$var reg 1 # reset $end
$var reg 1 $ set $end
$upscope $end
$enddefinitions $end
#0
$dumpvars
0$
0#
0"
1!
$end
#20
0!
1"
1$
#21
0$
#61
1$
#66
0$
#73
1!
0"
1#
#76
0#
#90
1#
#93
0#
#114
0!
1"
1$
#116
0$
#125
1!
0"
1#
#134
0#
