src/edsac/control_section/tank_decoder0.v
/* Copyright 2017 Hatim Kanchwala
 *
 * Contributor Hatim Kanchwala <hatim@hatimak.me>
 *
 * This file is licensed under the CERN OHL v. 1.2. You may redistribute and 
 * modify this documentation under the terms of the 
 * CERN OHL v.1.2. (http://ohwr.org/cernohl). This documentation is distributed 
 * WITHOUT ANY EXPRESS OR IMPLIED WARRANTY, INCLUDING OF MERCHANTABILITY, 
 * SATISFACTORY QUALITY AND FITNESS FOR A PARTICULAR PURPOSE. Please see the 
 * CERN OHL v.1.2 for applicable conditions.
 */
 
 /* The original machine's initial version had 32 Memory Tanks, 
 * distributed over four racks (8 Tanks per rack). Each Tank was
 * capable of holding 16 full words of 36 bits length 72 us delay. 
 * 
 * This is the first stage of Tank decoding. Uses two most significant 
 * bits of the Tank Number field (bits 10 and 11, corresponding to 
 * f10_pos and f11_pos respectively) to determine rack to be 
 * selected - F1, F2, R1 or R2. Additional control signal, c17a gated 
 * with cu_gate_pos, determines access type - read or write.
 */

module tank_decoder0 (
  output wire f1_read,
  output wire f1_write,
  output wire f2_read,
  output wire f2_write,
  output wire r1_read,
  output wire r1_write,
  output wire r2_read,
  output wire r2_write,

  input wire  c17a, // F, I, T, U, Starter order.
  input wire  f10_pos, // Tank address bit 10.
  input wire  f11_pos, // Tank address bit 11.
  input wire  cu_gate_pos // Coincidence gate.
  );

  /*  c17a  f11_pos  f10_pos  |
  * -------------------------+----------------------
  *  0       0        0      | f1_read  (0000_0001)
  *  0       0        1      | f2_read  (0000_0010)
  *  0       1        0      | r1_read  (0000_0100)
  *  0       1        1      | r2_read  (0000_1000)
  *  1       0        0      | f1_write (0001_0000)
  *  1       0        1      | f2_write (0010_0000)
  *  1       1        0      | r1_write (0100_0000)
  *  1       1        1      | r2_write (1000_0000)
  */
  assign {r2_write, r1_write, f2_write, f1_write, r2_read, r1_read, f2_read, f1_read} = cu_gate_pos ? (8'b0000_0001 << {c17a, f11_pos, f10_pos}) : 8'b0000_0000;

endmodule

test/edsac/control_section/tank_decoder0_tb.v
module tank_decoder0_tb();

   reg [2:0] count; // count[2] corresponds to c17a, count[1] to f11_pos, 0 to f10_pos.
   reg       cu_gate;
   wire      f1_read;
   wire      f1_write;
   wire      f2_read;
   wire      f2_write;
   wire      r1_read;
   wire      r1_write;
   wire      r2_read;
   wire      r2_write;

   tank_decoder0 td0
     (.f1_read     (f1_read),
      .f1_write    (f1_write),
      .f2_read     (f2_read),
      .f2_write    (f2_write),
      .r1_read     (r1_read),
      .r1_write    (r1_write),
      .r2_read     (r2_read),
      .r2_write    (r2_write),

      .c17a        (count[2]),
      .f10_pos     (count[0]),
      .f11_pos     (count[1]),
      .cu_gate_pos (cu_gate)
     );

   initial begin
      $dumpfile("tank_decoder0.vcd");
      $dumpvars(0, tank_decoder0_tb);
      cu_gate = 1'b0;
      count = 3'b000;
      #60 cu_gate = 1'b1;
      #300 $finish;
   end

   always #10 count = count + 3'b001;

endmodule

test/edsac/control_section/tank_decoder0.vcd
$date
	Mon Jun 12 23:18:10 2017
$end
$version
	Icarus Verilog
$end
$timescale
	1s
$end
$scope module tank_decoder0_tb $end
$var wire 1 ! r2_write $end
$var wire 1 " r2_read $end
$var wire 1 # r1_write $end
$var wire 1 $ r1_read $end
$var wire 1 % f2_write $end
$var wire 1 & f2_read $end
$var wire 1 ' f1_write $end
$var wire 1 ( f1_read $end
$var reg 3 ) count [2:0] $end
$var reg 1 * cu_gate $end
$scope module td0 $end
$var wire 1 + c17a $end
$var wire 1 * cu_gate_pos $end
$var wire 1 , f10_pos $end
$var wire 1 - f11_pos $end
$var wire 1 ! r2_write $end
$var wire 1 " r2_read $end
$var wire 1 # r1_write $end
$var wire 1 $ r1_read $end
$var wire 1 % f2_write $end
$var wire 1 & f2_read $end
$var wire 1 ' f1_write $end
$var wire 1 ( f1_read $end
$upscope $end
$upscope $end
$enddefinitions $end
#0
$dumpvars
0-
0,
0+
0*
b0 )
0(
0'
0&
0%
0$
0#
0"
0!
$end
#10
1,
b1 )
#20
0,
1-
b10 )
#30
1,
b11 )
#40
1+
0,
0-
b100 )
#50
1,
b101 )
#60
1#
0%
0,
1-
b110 )
1*
#70
0#
1!
1,
b111 )
#80
1(
0!
0+
0,
0-
b0 )
#90
0(
1&
1,
b1 )
#100
0&
1$
0,
1-
b10 )
#110
0$
1"
1,
b11 )
#120
0"
1'
1+
0,
0-
b100 )
#130
0'
1%
1,
b101 )
#140
0%
1#
0,
1-
b110 )
#150
0#
1!
1,
b111 )
#160
1(
0!
0+
0,
0-
b0 )
#170
0(
1&
1,
b1 )
#180
0&
1$
0,
1-
b10 )
#190
0$
1"
1,
b11 )
#200
0"
1'
1+
0,
0-
b100 )
#210
0'
1%
1,
b101 )
#220
0%
1#
0,
1-
b110 )
#230
0#
1!
1,
b111 )
#240
1(
0!
0+
0,
0-
b0 )
#250
0(
1&
1,
b1 )
#260
0&
1$
0,
1-
b10 )
#270
0$
1"
1,
b11 )
#280
0"
1'
1+
0,
0-
b100 )
#290
0'
1%
1,
b101 )
#300
0%
1#
0,
1-
b110 )
#310
0#
1!
1,
b111 )
#320
1(
0!
0+
0,
0-
b0 )
#330
0(
1&
1,
b1 )
#340
0&
1$
0,
1-
b10 )
#350
0$
1"
1,
b11 )
#360
0"
1'
1+
0,
0-
b100 )
