src/edsac/memory/delay_line.v
module delay_line
  #(parameter STORE_LEN  = 16,
    parameter WORD_WIDTH = 36
   )
   (output reg [STORE_LEN*WORD_WIDTH-1:0] monitor,
    output reg                            data_out,

    input wire                            clk,
    input wire                            data_in,
    input wire                            data_in_gate,
    input wire                            data_clr // Active low.
   );

   reg [STORE_LEN*WORD_WIDTH-1:0] store;
   integer                        i;

   initial begin
      // Assuming stores in delay lines were cleared.
      monitor = 0;
      store = 0;
      data_out = 1'b0;
   end

   // Recirculation logic.
   always @(posedge clk) begin
      for (i = 0; i < STORE_LEN*WORD_WIDTH-1; i = i + 1)
        store[i] <= store[i+1];

      store[STORE_LEN*WORD_WIDTH-1] <= (data_in_gate) ? data_in : (store[0] & data_clr);
   end

   always @(negedge clk) begin
      monitor[STORE_LEN*WORD_WIDTH-1:0] <= store[STORE_LEN*WORD_WIDTH-1:0];
      data_out <= store[0];
   end

endmodule

test/edsac/memory/delay_line_tb.v
`timescale 1ns / 1ps

module delay_line_tb();

   wire [3:0] monitor;
   wire       data_out;
   reg        clk = 1'b0;
   reg        data_in = 1'b0;
   reg        data_in_gate = 1'b0;
   reg        data_clr = 1'b1;

   delay_line #(2, 2) dl_uut
     (.monitor(monitor),
      .data_out(data_out),
      .clk(clk),
      .data_in(data_in),
      .data_in_gate(data_in_gate),
      .data_clr(data_clr)
     );

   initial begin
      $dumpfile("delay_line.vcd");
      $dumpvars(1, delay_line_tb);

      #17 data_in_gate = 1'b1;
      data_in = 1'b1;
      #19 data_in = 1'b0;
      #24 data_in_gate = 1'b0;

      #13 data_clr = 1'b0;
      #42 data_clr = 1'b1;

      #23 $finish;
   end

   always #5 clk = ~clk;

endmodule

test/edsac/memory/delay_line.vcd
$date
	Sun Jun 11 17:53:50 2017
$end
$version
	Icarus Verilog
$end
$timescale
	1ps
$end
$scope module delay_line_tb $end
$var wire 4 ! monitor [3:0] $end
$var wire 1 " data_out $end
$var reg 1 # clk $end
$var reg 1 $ data_clr $end
$var reg 1 % data_in $end
$var reg 1 & data_in_gate $end
$upscope $end
$enddefinitions $end
#0
$dumpvars
0&
0%
1$
0#
0"
b0 !
$end
#5000
1#
#10000
0#
#15000
1#
#17000
1%
1&
#20000
0#
#25000
1#
#30000
b1000 !
0#
#35000
1#
#36000
0%
#40000
b1100 !
0#
#45000
1#
#50000
b110 !
0#
#55000
1#
#60000
1"
b11 !
0#
0&
#65000
1#
#70000
b1001 !
0#
#73000
0$
#75000
1#
#80000
0"
b100 !
0#
#85000
1#
#90000
b10 !
0#
#95000
1#
#100000
1"
b1 !
0#
#105000
1#
#110000
0"
b0 !
0#
#115000
1#
1$
