src/edsac/memory/delay_line.v
module delay_line
  #(parameter STORE_LEN  = 16,
    parameter WORD_WIDTH = 36
   )
   (output reg [STORE_LEN*WORD_WIDTH-1:0] monitor,
    output reg                            data_out,

    input wire                            clk,
    input wire                            data_in,
    input wire                            data_in_gate,
    input wire                            data_clr // Active low.
   );

   reg [STORE_LEN*WORD_WIDTH-1:0] store;
   integer                        i;

   initial begin
      // Assuming stores in delay lines were cleared.
      monitor = 0;
      store = 0;
      data_out = 1'b0;
   end

   // Recirculation logic.
   always @(posedge clk) begin
      for (i = 0; i < STORE_LEN*WORD_WIDTH-1; i = i + 1)
        store[i] <= store[i+1];

      store[STORE_LEN*WORD_WIDTH-1] <= (data_in_gate) ? data_in : (store[0] & data_clr);
   end

   always @(negedge clk) begin
      monitor[STORE_LEN*WORD_WIDTH-1:0] <= store[STORE_LEN*WORD_WIDTH-1:0];
      data_out <= store[0];
   end

endmodule

src/edsac/memory/delay.v
module delay
  #(parameter INTERVAL = 1
   )
   (output wire out,

    input wire  clk,
    input wire  in
   );

   reg data_clr = 1'b1;
   reg data_in_gate = 1'b1;

   delay_line #(.STORE_LEN(1), .WORD_WIDTH(INTERVAL)) dl
     (.monitor      (),
      .data_out     (out),

      .clk          (clk),
      .data_in      (in),
      .data_in_gate (data_in_gate),
      .data_clr     (data_clr)
     );

endmodule

test/edsac/memory/delay_tb.v
`timescale 1ns / 1ps

module delay_tb();

   wire out1;
   wire out2;
   wire out3;
   reg  clk = 1'b0;
   reg  in = 1'b0;

   delay #(1) dl1_uut
     (.out (out1),

      .clk (clk),
      .in  (in)
     );

   delay #(2) dl2_uut
     (.out (out2),

      .clk (clk),
      .in  (in)
     );

   delay #(1) dl4_uut
     (.out (out3),

      .clk (clk),
      .in  (out1)
     );

   initial begin
      $dumpfile("delay.vcd");
      $dumpvars(1, delay_tb);

      #120 $finish;
   end

   always #5 clk = ~clk;

   always begin
      #10 in = 1'b1;
      #10 in = 1'b0;
      #20 in = 1'b1;
      #20 in = 1'b0;
      #30 in = 1'b1;
      #10 in = 1'b0;
   end

endmodule

test/edsac/memory/delay.vcd
$date
	Tue Jun  6 08:03:42 2017
$end
$version
	Icarus Verilog
$end
$timescale
	1ps
$end
$scope module delay_tb $end
$var wire 1 ! out3 $end
$var wire 1 " out2 $end
$var wire 1 # out1 $end
$var reg 1 $ clk $end
$var reg 1 % in $end
$upscope $end
$enddefinitions $end
#0
$dumpvars
0%
0$
0#
0"
0!
$end
#5000
1$
#10000
0$
1%
#15000
1$
#20000
1#
0$
0%
#25000
1$
#30000
1!
1"
0#
0$
#35000
1$
#40000
0"
0!
0$
1%
#45000
1$
#50000
1#
0$
#55000
1$
#60000
1"
1!
0$
0%
#65000
1$
#70000
0#
0$
#75000
1$
#80000
0"
0!
0$
#85000
1$
#90000
0$
1%
#95000
1$
#100000
1#
0$
0%
#105000
1$
#110000
1!
1"
0#
0$
1%
#115000
1$
#120000
1#
0"
0!
0$
0%
