src/edsac/memory/delay_line.v
module delay_line
  #(parameter STORE_LEN  = 16,
    parameter WORD_WIDTH = 36
    )
   (output wire [STORE_LEN*WORD_WIDTH-1:0] monitor,

    input wire                             clk,
    input wire                             data_in,
    input wire                             data_in_gate,
    input wire                             data_clr
   );

   reg [STORE_LEN*WORD_WIDTH-1:0] store;
   integer                        i;

   initial begin
      // Assuming stores in delay lines were cleared 
      // manually before commencing operation.
      store = 0;
   end

   // Recirculation logic.
   always @(posedge clk) begin
      for (i = 0; i < STORE_LEN*WORD_WIDTH-1; i = i + 1)
        store[i] <= store[i+1];

      // Assuming one bit is cleared with each clock cycle when 
      // data_clr is low (active low). Original machine behaviour 
      // documentation not found in this regard.
      if (data_in_gate)
        store[STORE_LEN*WORD_WIDTH-1] <= data_in;
      else if (~data_clr)
        store[STORE_LEN*WORD_WIDTH-1] <= 1'b0;
      else
        store[STORE_LEN*WORD_WIDTH-1] <= store[0];
   end

   assign monitor[STORE_LEN*WORD_WIDTH-1:0] = store[STORE_LEN*WORD_WIDTH-1:0];

endmodule

test/edsac/memory/delay_line_tb.v
`timescale 1ns / 1ps

module delay_line_tb();

   wire [3:0] monitor;
   reg        clk = 1'b0;
   reg        data_in = 1'b0;
   reg        data_in_gate = 1'b0;
   reg        data_clr = 1'b1;

   delay_line #(2, 2) dl1 (
                           .monitor(monitor),
                           .clk(clk),
                           .data_in(data_in),
                           .data_in_gate(data_in_gate),
                           .data_clr(data_clr)
                           );

   initial begin
      $dumpfile("delay_line.vcd");
      $dumpvars(1, delay_line_tb);

      #17 data_in_gate = 1'b1;
      data_in = 1'b1;
      data_in = 1'b1;
      #19 data_in = 1'b0;
      #24 data_in_gate = 1'b0;
      #13 data_clr = 1'b0;
      #66 data_clr = 1'b1;
      #43 $finish;
   end

   always #5 clk = ~clk;

endmodule

test/edsac/memory/delay_line.vcd
$date
	Sat Jun  3 23:32:02 2017
$end
$version
	Icarus Verilog
$end
$timescale
	1ps
$end
$scope module delay_line_tb $end
$var wire 4 ! monitor [3:0] $end
$var reg 1 " clk $end
$var reg 1 # data_clr $end
$var reg 1 $ data_in $end
$var reg 1 % data_in_gate $end
$upscope $end
$enddefinitions $end
#0
$dumpvars
0%
0$
1#
0"
b0 !
$end
#5000
1"
#10000
0"
#15000
1"
#17000
1$
1%
#20000
0"
#25000
b1000 !
1"
#30000
0"
#35000
b1100 !
1"
#36000
0$
#40000
0"
#45000
b110 !
1"
#50000
0"
#55000
b11 !
1"
#60000
0"
0%
#65000
b1001 !
1"
#70000
0"
#73000
0#
#75000
b100 !
1"
#80000
0"
#85000
b10 !
1"
#90000
0"
#95000
b1 !
1"
#100000
0"
#105000
b0 !
1"
#110000
0"
#115000
1"
#120000
0"
#125000
1"
#130000
0"
#135000
1"
#139000
1#
